<?xml version="1.0" encoding="UTF-8" ?>
<!DOCTYPE mapper PUBLIC "-//mybatis.org//DTD Mapper 3.0//EN" "http://mybatis.org/dtd/mybatis-3-mapper.dtd" >
<mapper namespace="com.recruit.dao.gen.mapper.CompanyMapper" >
  <resultMap id="BaseResultMap" type="com.recruit.dao.gen.model.Company" >
    <id column="com_id" property="comId" jdbcType="INTEGER" />
    <result column="fullname" property="fullname" jdbcType="VARCHAR" />
    <result column="username" property="username" jdbcType="VARCHAR" />
    <result column="user_id" property="userId" jdbcType="INTEGER" />
    <result column="comtype" property="comtype" jdbcType="VARCHAR" />
    <result column="description" property="description" jdbcType="VARCHAR" />
    <result column="empcount" property="empcount" jdbcType="VARCHAR" />
    <result column="address" property="address" jdbcType="VARCHAR" />
    <result column="email" property="email" jdbcType="VARCHAR" />
    <result column="tel" property="tel" jdbcType="VARCHAR" />
    <result column="manager" property="manager" jdbcType="VARCHAR" />
    <result column="m_tel" property="mTel" jdbcType="VARCHAR" />
  </resultMap>
  <sql id="Example_Where_Clause" >
    <where >
      <foreach collection="oredCriteria" item="criteria" separator="or" >
        <if test="criteria.valid" >
          <trim prefix="(" suffix=")" prefixOverrides="and" >
            <foreach collection="criteria.criteria" item="criterion" >
              <choose >
                <when test="criterion.noValue" >
                  and ${criterion.condition}
                </when>
                <when test="criterion.singleValue" >
                  and ${criterion.condition} #{criterion.value}
                </when>
                <when test="criterion.betweenValue" >
                  and ${criterion.condition} #{criterion.value} and #{criterion.secondValue}
                </when>
                <when test="criterion.listValue" >
                  and ${criterion.condition}
                  <foreach collection="criterion.value" item="listItem" open="(" close=")" separator="," >
                    #{listItem}
                  </foreach>
                </when>
              </choose>
            </foreach>
          </trim>
        </if>
      </foreach>
    </where>
  </sql>
  <sql id="Update_By_Example_Where_Clause" >
    <where >
      <foreach collection="example.oredCriteria" item="criteria" separator="or" >
        <if test="criteria.valid" >
          <trim prefix="(" suffix=")" prefixOverrides="and" >
            <foreach collection="criteria.criteria" item="criterion" >
              <choose >
                <when test="criterion.noValue" >
                  and ${criterion.condition}
                </when>
                <when test="criterion.singleValue" >
                  and ${criterion.condition} #{criterion.value}
                </when>
                <when test="criterion.betweenValue" >
                  and ${criterion.condition} #{criterion.value} and #{criterion.secondValue}
                </when>
                <when test="criterion.listValue" >
                  and ${criterion.condition}
                  <foreach collection="criterion.value" item="listItem" open="(" close=")" separator="," >
                    #{listItem}
                  </foreach>
                </when>
              </choose>
            </foreach>
          </trim>
        </if>
      </foreach>
    </where>
  </sql>
  <sql id="Base_Column_List" >
    com_id, fullname, username, user_id, comtype, description, empcount, address, email, 
    tel, manager, m_tel
  </sql>
  <select id="selectByExample" resultMap="BaseResultMap" parameterType="com.recruit.dao.gen.model.CompanyCriteria" >
    select
    <if test="distinct" >
      distinct
    </if>
    <include refid="Base_Column_List" />
    from company
    <if test="_parameter != null" >
      <include refid="Example_Where_Clause" />
    </if>
    <if test="orderByClause != null" >
      order by ${orderByClause}
    </if>
  </select>
  <select id="selectByPrimaryKey" resultMap="BaseResultMap" parameterType="java.lang.Integer" >
    select 
    <include refid="Base_Column_List" />
    from company
    where com_id = #{comId,jdbcType=INTEGER}
  </select>
  

  
 
  
  <delete id="deleteByExample" parameterType="com.recruit.dao.gen.model.CompanyCriteria" >
    delete from company
    <if test="_parameter != null" >
      <include refid="Example_Where_Clause" />
    </if>
  </delete>
  <insert id="insert" parameterType="com.recruit.dao.gen.model.Company" useGeneratedKeys="true" keyProperty="comId" >
    insert into company (fullname, username, user_id, 
      comtype, description, empcount, 
      address, email, tel, 
      manager, m_tel)
    values (#{fullname,jdbcType=VARCHAR}, #{username,jdbcType=VARCHAR}, #{userId,jdbcType=INTEGER}, 
      #{comtype,jdbcType=VARCHAR}, #{description,jdbcType=VARCHAR}, #{empcount,jdbcType=VARCHAR}, 
      #{address,jdbcType=VARCHAR}, #{email,jdbcType=VARCHAR}, #{tel,jdbcType=VARCHAR}, 
      #{manager,jdbcType=VARCHAR}, #{mTel,jdbcType=VARCHAR})
  </insert>
  <insert id="insertSelective" parameterType="com.recruit.dao.gen.model.Company" useGeneratedKeys="true" keyProperty="comId" >
    insert into company
    <trim prefix="(" suffix=")" suffixOverrides="," >
      <if test="fullname != null" >
        fullname,
      </if>
      <if test="username != null" >
        username,
      </if>
      <if test="userId != null" >
        user_id,
      </if>
      <if test="comtype != null" >
        comtype,
      </if>
      <if test="description != null" >
        description,
      </if>
      <if test="empcount != null" >
        empcount,
      </if>
      <if test="address != null" >
        address,
      </if>
      <if test="email != null" >
        email,
      </if>
      <if test="tel != null" >
        tel,
      </if>
      <if test="manager != null" >
        manager,
      </if>
      <if test="mTel != null" >
        m_tel,
      </if>
    </trim>
    <trim prefix="values (" suffix=")" suffixOverrides="," >
      <if test="fullname != null" >
        #{fullname,jdbcType=VARCHAR},
      </if>
      <if test="username != null" >
        #{username,jdbcType=VARCHAR},
      </if>
      <if test="userId != null" >
        #{userId,jdbcType=INTEGER},
      </if>
      <if test="comtype != null" >
        #{comtype,jdbcType=VARCHAR},
      </if>
      <if test="description != null" >
        #{description,jdbcType=VARCHAR},
      </if>
      <if test="empcount != null" >
        #{empcount,jdbcType=VARCHAR},
      </if>
      <if test="address != null" >
        #{address,jdbcType=VARCHAR},
      </if>
      <if test="email != null" >
        #{email,jdbcType=VARCHAR},
      </if>
      <if test="tel != null" >
        #{tel,jdbcType=VARCHAR},
      </if>
      <if test="manager != null" >
        #{manager,jdbcType=VARCHAR},
      </if>
      <if test="mTel != null" >
        #{mTel,jdbcType=VARCHAR},
      </if>
    </trim>
  </insert>
  <select id="countByExample" parameterType="com.recruit.dao.gen.model.CompanyCriteria" resultType="java.lang.Integer" >
    select count(*) from company
    <if test="_parameter != null" >
      <include refid="Example_Where_Clause" />
    </if>
  </select>
  <update id="updateByExampleSelective" parameterType="map" >
    update company
    <set >
      <if test="record.comId != null" >
        com_id = #{record.comId,jdbcType=INTEGER},
      </if>
      <if test="record.fullname != null" >
        fullname = #{record.fullname,jdbcType=VARCHAR},
      </if>
      <if test="record.username != null" >
        username = #{record.username,jdbcType=VARCHAR},
      </if>
      <if test="record.userId != null" >
        user_id = #{record.userId,jdbcType=INTEGER},
      </if>
      <if test="record.comtype != null" >
        comtype = #{record.comtype,jdbcType=VARCHAR},
      </if>
      <if test="record.description != null" >
        description = #{record.description,jdbcType=VARCHAR},
      </if>
      <if test="record.empcount != null" >
        empcount = #{record.empcount,jdbcType=VARCHAR},
      </if>
      <if test="record.address != null" >
        address = #{record.address,jdbcType=VARCHAR},
      </if>
      <if test="record.email != null" >
        email = #{record.email,jdbcType=VARCHAR},
      </if>
      <if test="record.tel != null" >
        tel = #{record.tel,jdbcType=VARCHAR},
      </if>
      <if test="record.manager != null" >
        manager = #{record.manager,jdbcType=VARCHAR},
      </if>
      <if test="record.mTel != null" >
        m_tel = #{record.mTel,jdbcType=VARCHAR},
      </if>
    </set>
    <if test="_parameter != null" >
      <include refid="Update_By_Example_Where_Clause" />
    </if>
  </update>
  <update id="updateByExample" parameterType="map" >
    update company
    set com_id = #{record.comId,jdbcType=INTEGER},
      fullname = #{record.fullname,jdbcType=VARCHAR},
      username = #{record.username,jdbcType=VARCHAR},
      user_id = #{record.userId,jdbcType=INTEGER},
      comtype = #{record.comtype,jdbcType=VARCHAR},
      description = #{record.description,jdbcType=VARCHAR},
      empcount = #{record.empcount,jdbcType=VARCHAR},
      address = #{record.address,jdbcType=VARCHAR},
      email = #{record.email,jdbcType=VARCHAR},
      tel = #{record.tel,jdbcType=VARCHAR},
      manager = #{record.manager,jdbcType=VARCHAR},
      m_tel = #{record.mTel,jdbcType=VARCHAR}
    <if test="_parameter != null" >
      <include refid="Update_By_Example_Where_Clause" />
    </if>
  </update>
  <update id="updateByPrimaryKeySelective" parameterType="com.recruit.dao.gen.model.Company" >
    update company
    <set >
      <if test="fullname != null" >
        fullname = #{fullname,jdbcType=VARCHAR},
      </if>
      <if test="username != null" >
        username = #{username,jdbcType=VARCHAR},
      </if>
      <if test="userId != null" >
        user_id = #{userId,jdbcType=INTEGER},
      </if>
      <if test="comtype != null" >
        comtype = #{comtype,jdbcType=VARCHAR},
      </if>
      <if test="description != null" >
        description = #{description,jdbcType=VARCHAR},
      </if>
      <if test="empcount != null" >
        empcount = #{empcount,jdbcType=VARCHAR},
      </if>
      <if test="address != null" >
        address = #{address,jdbcType=VARCHAR},
      </if>
      <if test="email != null" >
        email = #{email,jdbcType=VARCHAR},
      </if>
      <if test="tel != null" >
        tel = #{tel,jdbcType=VARCHAR},
      </if>
      <if test="manager != null" >
        manager = #{manager,jdbcType=VARCHAR},
      </if>
      <if test="mTel != null" >
        m_tel = #{mTel,jdbcType=VARCHAR},
      </if>
    </set>
    where com_id = #{comId,jdbcType=INTEGER}
  </update>
  <update id="updateByPrimaryKey" parameterType="com.recruit.dao.gen.model.Company" >
    update company
    set fullname = #{fullname,jdbcType=VARCHAR},
      username = #{username,jdbcType=VARCHAR},
      user_id = #{userId,jdbcType=INTEGER},
      comtype = #{comtype,jdbcType=VARCHAR},
      description = #{description,jdbcType=VARCHAR},
      empcount = #{empcount,jdbcType=VARCHAR},
      address = #{address,jdbcType=VARCHAR},
      email = #{email,jdbcType=VARCHAR},
      tel = #{tel,jdbcType=VARCHAR},
      manager = #{manager,jdbcType=VARCHAR},
      m_tel = #{mTel,jdbcType=VARCHAR}
    where com_id = #{comId,jdbcType=INTEGER}
  </update>
  
  <update id="updateByUserId" parameterType="com.recruit.dao.gen.model.Company" >
    update company
    <set >
      <if test="fullname != null" >
        fullname = #{fullname,jdbcType=VARCHAR},
      </if>
      <if test="comtype != null" >
        comtype = #{comtype,jdbcType=VARCHAR},
      </if>
      <if test="description != null" >
        description = #{description,jdbcType=VARCHAR},
      </if>
      <if test="empcount != null" >
        empcount = #{empcount,jdbcType=VARCHAR},
      </if>
      <if test="address != null" >
        address = #{address,jdbcType=VARCHAR},
      </if>
      <if test="email != null" >
        email = #{email,jdbcType=VARCHAR},
      </if>
      <if test="tel != null" >
        tel = #{tel,jdbcType=VARCHAR},
      </if>
      <if test="manager != null" >
        manager = #{manager,jdbcType=VARCHAR},
      </if>
      <if test="mTel != null" >
        m_tel = #{mTel,jdbcType=VARCHAR},
      </if>
    </set>
    where com_id = #{comId,jdbcType=INTEGER}
  </update>
  
    <delete id="deleteByPrimaryKey" parameterType="java.lang.Integer" >
    delete from company
    where user_id = #{user_Id,jdbcType=INTEGER}
  </delete>
  
</mapper>